nn_zoo/__init__.py
nn_zoo/datamodules/__init__.py
nn_zoo/datamodules/image/__init__.py
nn_zoo/datamodules/image/cifar.py
nn_zoo/datamodules/image/ffhq.py
nn_zoo/datamodules/image/mnist.py
nn_zoo/models/__init__.py
nn_zoo/models/utils.py
nn_zoo/models/components/__init__.py
nn_zoo/models/components/attention.py
nn_zoo/models/components/depthwise.py
nn_zoo/models/components/residual.py
nn_zoo/models/components/vq.py
nn_zoo/trainers/__init__.py
nn_zoo/trainers/classifier.py
nn_zoo/trainers/diffusion.py
nn_zoo/trainers/encoder.py
nn_zoo/trainers/encodergan.py
nn_zoo/trainers/seq_to_seq.py
nn_zoo/trainers/utils.py
nn_zoo-1.1.1.dist-info/LICENSE
nn_zoo-1.1.1.dist-info/METADATA
nn_zoo-1.1.1.dist-info/WHEEL
nn_zoo-1.1.1.dist-info/top_level.txt
nn_zoo-1.1.1.dist-info/RECORD
