Metadata-Version: 2.1
Name: nn-zoo
Version: 1.1.1
Summary: A collection of PyTorch utilities
Author-email: Karan Ravindra <contact@karanravindra.me>
License: MIT
Keywords: pytorch,machine-learning,deep-learning
Classifier: Intended Audience :: Developers
Classifier: Intended Audience :: Science/Research
Classifier: License :: OSI Approved :: MIT License
Classifier: Programming Language :: Python :: 3.11
Requires-Python: >=3.11
License-File: LICENSE
Requires-Dist: torch
Requires-Dist: torchvision
Requires-Dist: lightning
Requires-Dist: wandb
Requires-Dist: torchinfo
Provides-Extra: dev
Requires-Dist: pytest; extra == "dev"
Requires-Dist: ruff; extra == "dev"
Provides-Extra: publish
Requires-Dist: setuptools>=61; extra == "publish"
Requires-Dist: wheel; extra == "publish"
Requires-Dist: setuptools-scm[toml]>=6.0.1; extra == "publish"
Requires-Dist: build; extra == "publish"
